xkcd_parser/__init__.py
xkcd_parser/__main__.py
xkcd_parser/parser.py
xkcd_parser/py.typed
xkcd_parser-0.0.6a0.dist-info/licenses/LICENSE
xkcd_parser-0.0.6a0.dist-info/METADATA
xkcd_parser-0.0.6a0.dist-info/WHEEL
xkcd_parser-0.0.6a0.dist-info/entry_points.txt
xkcd_parser-0.0.6a0.dist-info/top_level.txt
xkcd_parser-0.0.6a0.dist-info/RECORD
