Metadata-Version: 2.4
Name: xkcd-parser
Version: 0.0.6a0
Summary: A library/cli tool to parse all comics' json from xkcd.com
Author-email: Sergey Sitnikov <aqendo@disroot.org>
License-Expression: MIT
Project-URL: Homepage, https://github.com/Aqendo/xkcd-parser
Project-URL: Issues, https://github.com/Aqendo/xkcd-parser/issues
Classifier: Development Status :: 3 - Alpha
Classifier: Operating System :: OS Independent
Classifier: Programming Language :: Python :: 3
Requires-Python: >=3.8
License-File: LICENSE
Requires-Dist: requests>=2.32.4
Dynamic: license-file
